LICENSE.txt
MANIFEST.in
README.rst
requirements.txt
setup.cfg
setup.py
minds/__init__.py
minds/check.py
minds/cover.py
minds/data.py
minds/dscheck.py
minds/lbxplus.py
minds/mcslsplus.py
minds/minds1.py
minds/mp92.py
minds/mxsatl.py
minds/mxsatls.py
minds/mxsatsp.py
minds/options.py
minds/rule.py
minds/ruler.py
minds/satl.py
minds/satls.py
minds/satr.py
minds/twostage.py
minds_kit.egg-info/PKG-INFO
minds_kit.egg-info/SOURCES.txt
minds_kit.egg-info/dependency_links.txt
minds_kit.egg-info/requires.txt
minds_kit.egg-info/top_level.txt
tool/mds.py