Metadata-Version: 2.1
Name: minds-kit
Version: 0.0.1.dev2
Summary: A SAT-based toolkit for learning optimal decision sets
Home-page: https://github.com/alexeyignatiev/minds
Author: Alexey Ignatiev
Author-email: alexey.ignatiev@monash.edu
License: MIT
Platform: UNKNOWN
